README.rst
setup.py
Eurydike.egg-info/PKG-INFO
Eurydike.egg-info/SOURCES.txt
Eurydike.egg-info/dependency_links.txt
Eurydike.egg-info/entry_points.txt
Eurydike.egg-info/requires.txt
Eurydike.egg-info/top_level.txt
eurydike/__init__.py
eurydike/eventdetectionmanager.py
eurydike/schema.py
eurydike/eventdetectors/__init__.py
eurydike/eventdetectors/abstracteventdetector.py
eurydike/eventdetectors/eventdetectorfactory.py
eurydike/eventdetectors/onband.py
eurydike/eventdetectors/onthreshold.py
tests_unit/__init__.py
tests_unit/test_eventdetectionmanager.py
tests_unit/test_onband.py
tests_unit/test_onthreshold.py
tests_unit/test_validateconfig.py